riroschool/__init__.py
riroschool/riroschool.py
yeoncho_riro-1.1.dist-info/METADATA
yeoncho_riro-1.1.dist-info/WHEEL
yeoncho_riro-1.1.dist-info/top_level.txt
yeoncho_riro-1.1.dist-info/RECORD
