Metadata-Version: 2.1
Name: yeoncho-riro
Version: 1.1
Summary: yeoncho-riroschool package
Home-page: https://github.com/bamcasa/yeoncho_riroschool
Author: bamcasa
Author-email: combeesang@gmail.com
License: MIT
Platform: UNKNOWN
Requires-Python: >=3
Requires-Dist: requests
Requires-Dist: beautifulsoup4
